peridata/__init__.py
peridata-1.3.3.post1.dist-info/LICENSE
peridata-1.3.3.post1.dist-info/METADATA
peridata-1.3.3.post1.dist-info/WHEEL
peridata-1.3.3.post1.dist-info/top_level.txt
peridata-1.3.3.post1.dist-info/RECORD
