Metadata-Version: 2.2
Name: peridata
Version: 1.3.3.post1
Summary: A tiny dictionary-like file storage system.
Author-email: whirlingstars <infernity@infernity.dev>
License: Unlicense
Keywords: STORAGE
Classifier: Development Status :: 5 - Production/Stable
Classifier: Intended Audience :: Developers
Classifier: License :: OSI Approved :: The Unlicense (Unlicense)
Classifier: Programming Language :: Python :: 3
Classifier: Programming Language :: Python :: 3.10
Classifier: Programming Language :: Python :: 3.11
Classifier: Programming Language :: Python :: 3.12
Classifier: Programming Language :: Python :: 3.13
License-File: LICENSE
